Metadata-Version: 2.1
Name: ourdishes
Version: 0.1
Summary: A library that displays one food dish every 24 hours from a list of dishes
Author: Meerath Nida Aman
Author-email: nidaaman77@gmail.com
Classifier: Development Status :: 3 - Alpha
Classifier: License :: OSI Approved :: MIT License
Classifier: Programming Language :: Python :: 3
Classifier: Programming Language :: Python :: 3.6
Classifier: Programming Language :: Python :: 3.7
Classifier: Programming Language :: Python :: 3.8
Classifier: Programming Language :: Python :: 3.9
